harmonize_wq/__init__.py
harmonize_wq/basis.py
harmonize_wq/clean.py
harmonize_wq/convert.py
harmonize_wq/domains.py
harmonize_wq/harmonize.py
harmonize_wq/location.py
harmonize_wq/visualize.py
harmonize_wq/wq_data.py
harmonize_wq/wrangle.py
harmonize_wq-0.5.0.dist-info/LICENSE
harmonize_wq-0.5.0.dist-info/METADATA
harmonize_wq-0.5.0.dist-info/WHEEL
harmonize_wq-0.5.0.dist-info/top_level.txt
harmonize_wq-0.5.0.dist-info/RECORD
