Metadata-Version: 2.1
Name: harmonize_wq
Version: 0.5.0
Summary: Package to standardize, clean, and wrangle Water Quality Portal data into more analytic-ready formats
Author-email: Justin Bousquin <Bousquin.Justin@epa.gov>
License: MIT License
Project-URL: Homepage, https://github.com/USEPA/harmonize-wq
Project-URL: Documentation, https://usepa.github.io/harmonize-wq/
Project-URL: Bug Tracker, https://github.com/USEPA/harmonize-wq/issues
Keywords: USEPA,water data,water quality
Classifier: Programming Language :: Python :: 3
Classifier: License :: OSI Approved :: MIT License
Classifier: Operating System :: OS Independent
Requires-Python: <3.12,>=3.8
License-File: LICENSE
Requires-Dist: numpy <2.0
Requires-Dist: pandas <2.0
Requires-Dist: geopandas <0.13,>=0.10.2
Requires-Dist: pint >=0.18
Requires-Dist: dataretrieval <1.0.5,>=1.0
Requires-Dist: descartes >=1.1.0
Requires-Dist: mapclassify >=2.4.0
Requires-Dist: requests
Provides-Extra: dev
